auto_labeler/__init__.py
auto_labeler/archive.py
auto_labeler/classify.py
auto_labeler/data_dir.py
auto_labeler/database.py
auto_labeler/errors.py
auto_labeler/gmail.py
auto_labeler/link.py
auto_labeler/main.py
auto_labeler/messages.py
auto_labeler/name_id_mapping.py
auto_labeler/train.py
auto_labeler/watermark.py
auto_labeler-0.1.2.dist-info/LICENSE
auto_labeler-0.1.2.dist-info/METADATA
auto_labeler-0.1.2.dist-info/WHEEL
auto_labeler-0.1.2.dist-info/entry_points.txt
auto_labeler-0.1.2.dist-info/RECORD
