Metadata-Version: 2.1
Name: auto-labeler
Version: 0.1.2
Summary: A simple tool for automatically labeling and archiving emails based on your past activity
Author: Brian Smith
Author-email: ohohvi@gmail.com
Requires-Python: >=3.10,<3.13
Classifier: Programming Language :: Python :: 3
Classifier: Programming Language :: Python :: 3.10
Classifier: Programming Language :: Python :: 3.11
Requires-Dist: appdirs (>=1.4.4,<2.0.0)
Requires-Dist: beautifulsoup4 (>=4.12.2,<5.0.0)
Requires-Dist: google-api-python-client (>=2.104.0,<3.0.0)
Requires-Dist: google-auth-httplib2 (>=0.1.1,<0.2.0)
Requires-Dist: google-auth-oauthlib (>=1.1.0,<2.0.0)
Requires-Dist: model-personal-trainer (>=0.1.0,<0.2.0)
Requires-Dist: tabulate (>=0.9.0,<0.10.0)
